grs/__init__.py
grs/best_buy_or_sell.py
grs/error.py
grs/fetch_data.py
grs/industry_code.csv
grs/industry_code_otc.csv
grs/opendate.csv
grs/otc_list.csv
grs/realtime.py
grs/realtime2.py
grs/tw_time.py
grs/twse_list.csv
grs/twseno.py
grs/twseopen.py
grs-0.7.0.dist-info/DESCRIPTION.rst
grs-0.7.0.dist-info/METADATA
grs-0.7.0.dist-info/RECORD
grs-0.7.0.dist-info/WHEEL
grs-0.7.0.dist-info/metadata.json
grs-0.7.0.dist-info/top_level.txt
