Metadata-Version: 2.0
Name: grs
Version: 0.7.0
Summary: 台灣上市上櫃股票價格擷取（Fetch Taiwan Stock Exchange data）含即時盤、台灣時間轉換、開休市判斷。
Home-page: https://github.com/toomore/grs
Author: Toomore Chiang
Author-email: toomore0929@gmail.com
License: MIT
Keywords: Taiwan Stock Exchange taipei twse otc gretai 台灣 台北 股市 即時 上市 上櫃
Platform: UNKNOWN
Classifier: Development Status :: 5 - Production/Stable
Classifier: Environment :: Console
Classifier: Environment :: Web Environment
Classifier: Intended Audience :: End Users/Desktop
Classifier: Intended Audience :: Financial and Insurance Industry
Classifier: Intended Audience :: Developers
Classifier: License :: OSI Approved :: MIT License
Classifier: Natural Language :: Chinese (Traditional)
Classifier: Programming Language :: Python
Classifier: Programming Language :: Python :: 2.7
Classifier: Topic :: Office/Business :: Financial :: Investment
Requires-Dist: python-dateutil (==1.5)
Requires-Dist: ujson
Requires-Dist: urllib3
